LICENSE
MANIFEST.in
README.rst
VERSION
setup.py
version.txt
pkiutils/__init__.py
pkiutils/__main__.py
pkiutils.egg-info/PKG-INFO
pkiutils.egg-info/SOURCES.txt
pkiutils.egg-info/dependency_links.txt
pkiutils.egg-info/requires.txt
pkiutils.egg-info/top_level.txt