Metadata-Version: 1.0
Name: pkiutils
Version: 0.1
Summary: a set of public key infrastructure utilities
Home-page: https://github.com/jandd/python-pkiutils
Author: Jan Dittberner
Author-email: jan@dittberner.info
License: MIT
Platform: UNKNOWN
